{
  "type": "minecraft:chest",
  "pools": [
    {
      "bonus_rolls": 0.0,
      "entries": [
        {
          "type": "minecraft:item",
          "name": "minecraft:echo_shard",
          "weight": 2
        }
      ],
      "rolls": {
        "type": "minecraft:uniform",
        "max": 2.0,
        "min": 1.0
      }
    },
    {
      "bonus_rolls": 0.0,
      "entries": [
        {
          "type": "minecraft:item",
          "name": "minecraft:redstone",
          "weight": 2
        }
      ],
      "rolls": {
        "type": "minecraft:uniform",
        "max": 3.0,
        "min": 1.0
      }
    },
    {
      "bonus_rolls": 0.0,
      "entries": [
        {
          "type": "minecraft:item",
          "functions": [
            {
              "add": false,
              "count": {
                "type": "minecraft:uniform",
                "max": 4.0,
                "min": 1.0
              },
              "function": "minecraft:set_count"
            }
          ],
          "name": "ceilands:polished_ceilingneous",
          "weight": 2
        },
        {
          "type": "minecraft:item",
          "functions": [
            {
              "add": false,
              "count": {
                "type": "minecraft:uniform",
                "max": 4.0,
                "min": 1.0
              },
              "function": "minecraft:set_count"
            }
          ],
          "name": "ceilands:ceilingneous",
          "weight": 3
        }
      ],
      "rolls": {
        "type": "minecraft:uniform",
        "max": 3.0,
        "min": 1.0
      }
    },
    {
      "bonus_rolls": 0.0,
      "entries": [
        {
          "type": "minecraft:item",
          "functions": [
            {
              "add": false,
              "count": {
                "type": "minecraft:uniform",
                "max": 4.0,
                "min": 1.0
              },
              "function": "minecraft:set_count"
            }
          ],
          "name": "minecraft:blaze_powder",
          "weight": 5
        },
        {
          "type": "minecraft:item",
          "functions": [
            {
              "add": false,
              "count": {
                "type": "minecraft:uniform",
                "max": 2.0,
                "min": 1.0
              },
              "function": "minecraft:set_count"
            }
          ],
          "name": "minecraft:blaze_rod",
          "weight": 2
        },
        {
          "type": "minecraft:item",
          "functions": [
            {
              "add": false,
              "count": {
                "type": "minecraft:uniform",
                "max": 2.0,
                "min": 1.0
              },
              "function": "minecraft:set_count"
            }
          ],
          "name": "minecraft:gunpowder",
          "weight": 2
        },
        {
          "type": "minecraft:item",
          "functions": [
            {
              "add": false,
              "count": {
                "type": "minecraft:uniform",
                "max": 1.0,
                "min": 1.0
              },
              "function": "minecraft:set_count"
            }
          ],
          "name": "minecraft:fire_charge",
          "weight": 1
        }
      ],
      "rolls": {
        "type": "minecraft:uniform",
        "max": 2.0,
        "min": 1.0
      }
    }
  ]
}